{
  "formatVersion": 1,
  "database": {
    "version": 1,
    "identityHash": "c9b1d44d5b30571cf55b5d8a41c039c7",
    "entities": [
      {
        "tableName": "cities",
        "createSql": "CREATE TABLE IF NOT EXISTS `${TABLE_NAME}` (`id` INTEGER PRIMARY KEY AUTOINCREMENT NOT NULL, `name` TEXT NOT NULL, `foundedIn` TEXT NOT NULL)",
        "fields": [
          {
            "fieldPath": "id",
            "columnName": "id",
            "affinity": "INTEGER",
            "notNull": true
          },
          {
            "fieldPath": "name",
            "columnName": "name",
            "affinity": "TEXT",
            "notNull": true
          },
          {
            "fieldPath": "foundedIn",
            "columnName": "foundedIn",
            "affinity": "TEXT",
            "notNull": true
          }
        ],
        "primaryKey": {
          "autoGenerate": true,
          "columnNames": [
            "id"
          ]
        }
      },
      {
        "tableName": "cities_list_data",
        "createSql": "CREATE TABLE IF NOT EXISTS `${TABLE_NAME}` (`id` INTEGER PRIMARY KEY AUTOINCREMENT NOT NULL, `shortName` TEXT NOT NULL, `fullName` TEXT NOT NULL, `colorId` INTEGER NOT NULL, `citiesIds` TEXT NOT NULL)",
        "fields": [
          {
            "fieldPath": "id",
            "columnName": "id",
            "affinity": "INTEGER",
            "notNull": true
          },
          {
            "fieldPath": "shortName",
            "columnName": "shortName",
            "affinity": "TEXT",
            "notNull": true
          },
          {
            "fieldPath": "fullName",
            "columnName": "fullName",
            "affinity": "TEXT",
            "notNull": true
          },
          {
            "fieldPath": "colorId",
            "columnName": "colorId",
            "affinity": "INTEGER",
            "notNull": true
          },
          {
            "fieldPath": "citiesIds",
            "columnName": "citiesIds",
            "affinity": "TEXT",
            "notNull": true
          }
        ],
        "primaryKey": {
          "autoGenerate": true,
          "columnNames": [
            "id"
          ]
        }
      }
    ],
    "setupQueries": [
      "CREATE TABLE IF NOT EXISTS room_master_table (id INTEGER PRIMARY KEY,identity_hash TEXT)",
      "INSERT OR REPLACE INTO room_master_table (id,identity_hash) VALUES(42, 'c9b1d44d5b30571cf55b5d8a41c039c7')"
    ]
  }
}